hello_atlas/__init__.py
hello_atlas/atlas_basic_pipeline.py
hello_atlas/atlas_eda.py
hello_atlas/atlas_eda_wip.py
hello_atlas/atlas_nlp_pipeline.py
hello_atlas-0.0.8.dist-info/LICENSE
hello_atlas-0.0.8.dist-info/METADATA
hello_atlas-0.0.8.dist-info/WHEEL
hello_atlas-0.0.8.dist-info/top_level.txt
hello_atlas-0.0.8.dist-info/RECORD
