Metadata-Version: 2.1
Name: hello-atlas
Version: 0.0.8
Summary: Basic functionality for data science & engineering
Home-page: https://github.com/hello-atlas/hello-atlas
Author: Atlas
Author-email: helloatlas42@gmail.com
License: MIT
Platform: UNKNOWN
Classifier: Development Status :: 3 - Alpha
Classifier: License :: OSI Approved :: MIT License
Classifier: Intended Audience :: Developers
Classifier: Programming Language :: Python :: 3
Classifier: Programming Language :: Python :: 3.6
Classifier: Programming Language :: Python :: 3.7
Classifier: Operating System :: OS Independent
